FoxLabel/FoxLabel.py
FoxLabel/__init__.py
FoxLabel/libs/__init__.py
FoxLabel/libs/canvas.py
FoxLabel/libs/colorDialog.py
FoxLabel/libs/combobox.py
FoxLabel/libs/constants.py
FoxLabel/libs/create_ml_io.py
FoxLabel/libs/default_label_combobox.py
FoxLabel/libs/hashableQListWidgetItem.py
FoxLabel/libs/labelDialog.py
FoxLabel/libs/labelFile.py
FoxLabel/libs/lightWidget.py
FoxLabel/libs/pascal_voc_io.py
FoxLabel/libs/resources.py
FoxLabel/libs/settings.py
FoxLabel/libs/shape.py
FoxLabel/libs/stringBundle.py
FoxLabel/libs/toolBar.py
FoxLabel/libs/ustr.py
FoxLabel/libs/utils.py
FoxLabel/libs/yolo_io.py
FoxLabel/libs/zoomWidget.py
FoxLabel-1.3.dist-info/METADATA
FoxLabel-1.3.dist-info/WHEEL
FoxLabel-1.3.dist-info/entry_points.txt
FoxLabel-1.3.dist-info/top_level.txt
FoxLabel-1.3.dist-info/RECORD
