Metadata-Version: 2.1
Name: FoxLabel
Version: 1.3
Summary: Thư viện hữu ích của Tuấn Anh.
Home-page: https://pypi.org/project/FoxLabel/
Author: Tuấn Anh - Foxconn
Author-email: nt.anh.fai@gmail.com
License: MIT
Classifier: Programming Language :: Python :: 3
Classifier: License :: OSI Approved :: MIT License
Classifier: Operating System :: OS Independent
Requires-Dist: lxml
Requires-Dist: opencv-python
Requires-Dist: ruamel.yaml
Requires-Dist: pyyaml
Requires-Dist: ntanh
